taiyo/__init__.py
taiyo/types.py
taiyo/client/__init__.py
taiyo/client/auth.py
taiyo/client/base.py
taiyo/client/client.py
taiyo/params/__init__.py
taiyo/params/configs/__init__.py
taiyo/params/configs/base.py
taiyo/params/configs/facet.py
taiyo/params/configs/group.py
taiyo/params/configs/highlight.py
taiyo/params/configs/more_like_this.py
taiyo/params/mixins/__init__.py
taiyo/params/mixins/base.py
taiyo/params/mixins/common.py
taiyo/params/mixins/dense_vector_search.py
taiyo/params/mixins/spatial_search.py
taiyo/parsers/__init__.py
taiyo/parsers/base.py
taiyo/parsers/dense/__init__.py
taiyo/parsers/dense/base.py
taiyo/parsers/dense/knn.py
taiyo/parsers/dense/knn_text_to_vector.py
taiyo/parsers/dense/vector_similarity.py
taiyo/parsers/sparse/__init__.py
taiyo/parsers/sparse/dismax.py
taiyo/parsers/sparse/edismax.py
taiyo/parsers/sparse/lucene.py
taiyo/parsers/spatial/__init__.py
taiyo/parsers/spatial/base.py
taiyo/parsers/spatial/bbox.py
taiyo/parsers/spatial/geofilt.py
taiyo/parsers/terms/__init__.py
taiyo/parsers/terms/terms.py
taiyo/schema/__init__.py
taiyo/schema/copy_field.py
taiyo/schema/enums.py
taiyo/schema/field.py
taiyo/schema/field_type.py
taiyo/schema/schema.py
taiyo-0.1.5.dist-info/METADATA
taiyo-0.1.5.dist-info/WHEEL
taiyo-0.1.5.dist-info/licenses/LICENSE
taiyo-0.1.5.dist-info/RECORD
