Metadata-Version: 2.4
Name: taiyo
Version: 0.1.5
Summary: Modern Python client for Apache Solr with type safety and async support, built with httpx and Pydantic
Project-URL: homepage, https://github.com/taiyoproj/taiyo
Author-email: KengoA <kengo@hey.com>
License: Apache-2.0
License-File: LICENSE
Keywords: solr
Requires-Python: >=3.11
Requires-Dist: httpx>=0.24.0
Requires-Dist: pydantic>=2.0.0
Requires-Dist: typing-extensions>=4.5.0
Provides-Extra: dev
Requires-Dist: black>=23.0.0; extra == 'dev'
Requires-Dist: mypy>=1.0.0; extra == 'dev'
Requires-Dist: pytest-asyncio>=0.23.0; extra == 'dev'
Requires-Dist: pytest-cov>=4.0.0; extra == 'dev'
Requires-Dist: pytest>=7.0.0; extra == 'dev'
Requires-Dist: ruff>=0.0.270; extra == 'dev'
Requires-Dist: zensical>=0.0.9; extra == 'dev'
